vacationextender/__init__.py
vacationextender/core.py
vacationextender/main.py
vacationextender/mycalendar.py
vacation_extender-1.0.0.dist-info/METADATA
vacation_extender-1.0.0.dist-info/WHEEL
vacation_extender-1.0.0.dist-info/entry_points.txt
vacation_extender-1.0.0.dist-info/licenses/LICENSE
vacation_extender-1.0.0.dist-info/RECORD
