Metadata-Version: 2.4
Name: vacation-extender
Version: 1.0.0
Summary: Maximize time off by smart linking public holidays and weekends.
Project-URL: Homepage, https://github.com/afsmaira/vacationExtender
Project-URL: Bug Tracker, https://github.com/afsmaira/vacationExtender/issues
Project-URL: Changelog, https://github.com/afsmaira/vacationExtender/blob/main/CHANGELOG.md
Author-email: André de Freitas Smaira <andre.smaira@gmail.com>
License: MIT License
License-File: LICENSE
Keywords: holiday,optimization,planner,timeoff,vacation
Classifier: License :: OSI Approved :: MIT License
Classifier: Operating System :: OS Independent
Classifier: Programming Language :: Python :: 3
Requires-Python: >=3.8
Requires-Dist: holidays
Requires-Dist: streamlit
Requires-Dist: toml
